oamf/__init__.py
oamf/oamf.py
oamf/deployer/__init__.py
oamf/deployer/deploy.py
oamf/pipeline_builder/__init__.py
oamf/pipeline_builder/example_usage.ipynb
oamf/pipeline_builder/pipeline_builder.py
oamf/pipeline_builder/n8n/__init__.py
oamf/pipeline_builder/n8n/http_nodes.json
oamf/pipeline_builder/n8n/n8n_pipeline_executer.py
oamf-1.0.1.0.dist-info/METADATA
oamf-1.0.1.0.dist-info/WHEEL
oamf-1.0.1.0.dist-info/licenses/LICENSE
oamf-1.0.1.0.dist-info/RECORD
