Metadata-Version: 2.4
Name: oamf
Version: 1.0.1.0
Summary: oAMF package
Project-URL: Homepage, https://github.com/arg-tech/oamf
Project-URL: Issues, https://github.com/arg-tech/oamf/issues
Author-email: DEBELA <dabookoo@gmail.com>
License-File: LICENSE
Classifier: License :: OSI Approved :: MIT License
Classifier: Operating System :: OS Independent
Classifier: Programming Language :: Python :: 3
Requires-Python: >=3.8
Requires-Dist: networkx
Requires-Dist: pandas
Requires-Dist: pyyaml
